{
  "sectionTitle": "Access the Intelligence Layer of the Markets",
  "sectionSubtitle": "From research and exploration to full institutional-grade quantitative access — three tiers designed for every stage of systematic trading.",
  "disclaimer": "All plans provide informational AI-generated market signals. Not financial advice. Past performance does not guarantee future results.",
  "currency": "USD",
  "billingCycle": "monthly",
  "tiers": [
    {
      "id": "research",
      "name": "Research",
      "tagline": "Explore the platform and validate the models — free.",
      "price": 0,
      "priceLabel": "Free",
      "priceNote": "No credit card required",
      "cta": { "label": "Start Researching", "href": "/signup" },
      "dataLatency": "End-of-day (15-minute delay during market hours)",
      "limits": {
        "signals": "Momentum and Mean Reversion only",
        "assets": "S&P 500 equities + BTC/ETH",
        "apiCalls": "1,000/day",
        "backtestRuns": "10/month (5-year lookback max)",
        "monteCarloScenarios": 1000
      },
      "features": [
        "End-of-day Momentum signals (S&P 500 + BTC/ETH)",
        "End-of-day Mean Reversion signals",
        "Basic backtesting (5-year lookback, 1,000 Monte Carlo paths)",
        "1,000 API calls/day",
        "Signal performance tearsheets",
        "Community Discord access",
        "Python SDK (read-only)"
      ],
      "notIncluded": [
        "Real-time signals",
        "CSL Consensus, Phi Breakout, Sentiment, Volatility Surface",
        "Portfolio optimization",
        "Full backtesting suite",
        "WebSocket streaming"
      ],
      "badge": null
    },
    {
      "id": "pro-trader",
      "name": "Pro Trader",
      "tagline": "Real-time signals and full multi-asset coverage.",
      "price": 79,
      "priceLabel": "$79",
      "priceNote": "per month ($69/mo annual)",
      "cta": { "label": "Start Pro Trader", "href": "/signup?plan=pro" },
      "dataLatency": "Real-time (< 50ms signal publication latency)",
      "limits": {
        "signals": "Momentum, Mean Reversion, Phi Breakout, Sentiment Aggregate",
        "assets": "All equities (NYSE/NASDAQ/CBOE), top 50 crypto, 28 forex pairs",
        "apiCalls": "50,000/day",
        "backtestRuns": "100/month (10-year lookback)",
        "monteCarloScenarios": 10000
      },
      "features": [
        "Real-time Momentum, Mean Reversion, Phi Breakout signals",
        "Sentiment Aggregate signals (equities + crypto)",
        "All equities (S&P 500, Russell 2000, NASDAQ-100, global ADRs)",
        "Top 50 crypto by market cap (aggregated CEX feed)",
        "28 G10 + EM forex pairs",
        "Full backtesting suite (10-year lookback, 10,000 Monte Carlo paths)",
        "50,000 API calls/day",
        "WebSocket real-time signal streaming",
        "φ-Scaled risk model parameter customization",
        "Risk-adjusted performance analytics (Sharpe, Sortino, Calmar)",
        "Email/Slack signal alerts",
        "Python + TypeScript SDK",
        "Email support (24h response)"
      ],
      "notIncluded": [
        "CSL Consensus signals",
        "Volatility Surface signals",
        "Portfolio optimization engine",
        "Custom signal parameter tuning",
        "Priority API rate limits"
      ],
      "badge": "Most Popular"
    },
    {
      "id": "quant",
      "name": "Quant",
      "tagline": "Full API access, CSL Consensus signals, and the complete backtesting suite.",
      "price": 299,
      "priceLabel": "$299",
      "priceNote": "per month ($249/mo annual)",
      "cta": { "label": "Start Quant", "href": "/signup?plan=quant" },
      "dataLatency": "Real-time (< 35ms priority pipeline for CSL Consensus)",
      "limits": {
        "signals": "All 6 signal types including CSL Consensus and Volatility Surface",
        "assets": "All supported assets including equity options",
        "apiCalls": "Unlimited",
        "backtestRuns": "Unlimited",
        "monteCarloScenarios": "Unlimited (parallel compute)"
      },
      "features": [
        "All 6 signal types including CSL Consensus and Volatility Surface",
        "Equity options coverage (full IV surface, OCC data feed)",
        "Portfolio optimization engine (mean-variance, Black-Litterman, CVaR)",
        "Unlimited API calls with priority rate limit pools",
        "Unlimited backtesting with parallel Monte Carlo (unlimited paths)",
        "Full 15-year historical data access",
        "Custom signal parameter tuning via API",
        "WebSocket + FIX protocol connectivity (FIX adapter on request)",
        "Python, TypeScript, R SDKs",
        "Raw tick data export (CSV/Parquet)",
        "Dedicated Slack channel with Heady quant team",
        "4h SLA on API support tickets",
        "Access to pre-release signal types (beta)"
      ],
      "badge": "Full Access"
    }
  ]
}
